slidgnal/.gopy.sum
slidgnal/__init__.py
slidgnal/__main__.py
slidgnal/config.py
slidgnal/contact.py
slidgnal/event.go
slidgnal/gateway.go
slidgnal/gateway.py
slidgnal/generated/__init__.py
slidgnal/generated/_signal.cpython-313-aarch64-linux-gnu.h
slidgnal/generated/_signal.cpython-313-aarch64-linux-gnu.so
slidgnal/generated/build.py
slidgnal/generated/go.py
slidgnal/generated/signal.c
slidgnal/generated/signal.go
slidgnal/generated/signal.py
slidgnal/generated/signal_go.h
slidgnal/go.mod
slidgnal/go.sum
slidgnal/group.py
slidgnal/session.go
slidgnal/session.py
slidgnal/vendor/github.com/coder/websocket/LICENSE.txt
slidgnal/vendor/github.com/coder/websocket/Makefile
slidgnal/vendor/github.com/coder/websocket/README.md
slidgnal/vendor/github.com/coder/websocket/accept.go
slidgnal/vendor/github.com/coder/websocket/close.go
slidgnal/vendor/github.com/coder/websocket/compress.go
slidgnal/vendor/github.com/coder/websocket/conn.go
slidgnal/vendor/github.com/coder/websocket/dial.go
slidgnal/vendor/github.com/coder/websocket/doc.go
slidgnal/vendor/github.com/coder/websocket/errors.go
slidgnal/vendor/github.com/coder/websocket/frame.go
slidgnal/vendor/github.com/coder/websocket/hijack.go
slidgnal/vendor/github.com/coder/websocket/internal/bpool/bpool.go
slidgnal/vendor/github.com/coder/websocket/internal/errd/wrap.go
slidgnal/vendor/github.com/coder/websocket/internal/util/util.go
slidgnal/vendor/github.com/coder/websocket/internal/wsjs/wsjs_js.go
slidgnal/vendor/github.com/coder/websocket/mask.go
slidgnal/vendor/github.com/coder/websocket/mask_amd64.s
slidgnal/vendor/github.com/coder/websocket/mask_arm64.s
slidgnal/vendor/github.com/coder/websocket/mask_asm.go
slidgnal/vendor/github.com/coder/websocket/mask_go.go
slidgnal/vendor/github.com/coder/websocket/netconn.go
slidgnal/vendor/github.com/coder/websocket/netconn_js.go
slidgnal/vendor/github.com/coder/websocket/netconn_notjs.go
slidgnal/vendor/github.com/coder/websocket/read.go
slidgnal-0.3.0b9.dist-info/METADATA
slidgnal-0.3.0b9.dist-info/WHEEL
slidgnal-0.3.0b9.dist-info/entry_points.txt
slidgnal-0.3.0b9.dist-info/licenses/LICENSE
slidgnal-0.3.0b9.dist-info/RECORD
