Metadata-Version: 2.4
Name: slidgnal
Version: 0.3.0b9
Summary: A Signal/XMPP gateway
License-Expression: AGPL-3.0-or-later
License-File: LICENSE
Keywords: xmpp,gateway,bridge,instant messaging,chat,signal
Author: deuill
Author-email: alex@deuill.org
Requires-Python: >= 3.11
Classifier: Topic :: Internet :: XMPP
Requires-Dist: slidge (>=0.3.4.dev46,<0.4)
Project-URL: Chat room, https://slidge.im/xmpp-web/#/guest?join=support@rooms.slidge.im
Project-URL: Documentation, https://slidge.im/docs/slidgnal/main
Project-URL: Homepage, https://codeberg.org/slidge/slidgnal
Project-URL: Issues, https://codeberg.org/slidge/slidgnal/issues
Project-URL: Repository, https://codeberg.org/slidge/slidgnal
Project-URL: changelog, https://codeberg.org/slidge/slidgnal/releases
